preprocessing/__init__.py
preprocessing/clipping.py
preprocessing/files/__init__.py
preprocessing/files/config.py
preprocessing/files/file_handler.py
preprocessing/files/hdf5.py
preprocessing/files/json.py
preprocessing/files/npy.py
preprocessing/files/png.py
preprocessing/files/tif.py
preprocessing/files/utils.py
preprocessing/image_processing.py
preprocessing/main.py
preprocessing/sample_generate.py
nr29467_16_preprocessing-0.1.0.dist-info/METADATA
nr29467_16_preprocessing-0.1.0.dist-info/WHEEL
nr29467_16_preprocessing-0.1.0.dist-info/entry_points.txt
nr29467_16_preprocessing-0.1.0.dist-info/RECORD
