Metadata-Version: 2.1
Name: nr29467-16-preprocessing
Version: 0.1.0
Summary: Preprocessing for segmentation
Author: Pimblott, Matthew (DLSLtd,RAL,LSCI)
Author-email: matthew.pimblott@diamond.ac.uk
Requires-Python: ==3.11.3
Classifier: Programming Language :: Python :: 3
Requires-Dist: click (>=8.1.4,<9.0.0)
Requires-Dist: h5py (>=3.9.0,<4.0.0)
Requires-Dist: matplotlib (>=3.7.2,<4.0.0)
Requires-Dist: numpy (>=1.25.1,<2.0.0)
Requires-Dist: pandas (>=2.0.3,<3.0.0)
Requires-Dist: scikit-image (>=0.21.0,<0.22.0)
Requires-Dist: scikit-learn (>=1.3.0,<2.0.0)
Requires-Dist: scipy (>=1.11.1,<2.0.0)
Requires-Dist: tifffile (>=2023.7.10,<2024.0.0)
